{
  "generated_at": "2026-06-18T23:19:48.492479+00:00",
  "scenarios": [
    "normal_flow",
    "exit_blockage",
    "multimodal_conflict",
    "evacuation_recommendation",
    "crowd_acceleration",
    "audio_stress_signal"
  ],
  "seeds": [
    1,
    2,
    3,
    4,
    5,
    6,
    7,
    8,
    9,
    10,
    11,
    12,
    13,
    14,
    15,
    16,
    17,
    18,
    19,
    20,
    21,
    22,
    23,
    24,
    25,
    26,
    27,
    28,
    29,
    30
  ],
  "lambdas": [
    0.0,
    0.25,
    0.5,
    0.75,
    1.0
  ],
  "channels": [
    "zone_permutation",
    "temporal_desync",
    "noise_injection"
  ],
  "chance_permutations": 1000,
  "disclaimer": "Coupling-controlled PAR decomposition: diagnostic experiment only. Perturbations corrupt emitter-visible simulator variables while the ground-truth oracle remains on clean state. Not operational safety, deployment validity, or a new headline superiority claim.",
  "aggregate": [
    {
      "channel": "zone_permutation",
      "lambda": 0.0,
      "coupling_proxy": 1.0,
      "par": 0.9249,
      "fpr": 0.0089,
      "fnr": 0.0673,
      "par_ci_95": [
        0.9062,
        0.9287
      ],
      "par_zero": 0.9177,
      "par_zero_ci_95": [
        0.9062,
        0.9287
      ],
      "delta_proc": 0.0,
      "delta_proc_ci_95": [
        0.0,
        0.0
      ],
      "par_decay_slope": null
    },
    {
      "channel": "zone_permutation",
      "lambda": 0.25,
      "coupling_proxy": 0.884,
      "par": 0.8884,
      "fpr": 0.0028,
      "fnr": 0.1093,
      "par_ci_95": [
        0.837,
        0.8743
      ],
      "par_zero": 0.8558,
      "par_zero_ci_95": [
        0.837,
        0.8743
      ],
      "delta_proc": 0.0,
      "delta_proc_ci_95": [
        0.0,
        0.0
      ],
      "par_decay_slope": null
    },
    {
      "channel": "zone_permutation",
      "lambda": 0.5,
      "coupling_proxy": 0.7773,
      "par": 0.8478,
      "fpr": 0.0007,
      "fnr": 0.1517,
      "par_ci_95": [
        0.7655,
        0.8195
      ],
      "par_zero": 0.7927,
      "par_zero_ci_95": [
        0.7655,
        0.8195
      ],
      "delta_proc": 0.0,
      "delta_proc_ci_95": [
        0.0,
        0.0
      ],
      "par_decay_slope": null
    },
    {
      "channel": "zone_permutation",
      "lambda": 0.75,
      "coupling_proxy": 0.6687,
      "par": 0.8066,
      "fpr": 0.0004,
      "fnr": 0.1931,
      "par_ci_95": [
        0.6926,
        0.7614
      ],
      "par_zero": 0.7268,
      "par_zero_ci_95": [
        0.6926,
        0.7614
      ],
      "delta_proc": 0.0,
      "delta_proc_ci_95": [
        0.0,
        0.0
      ],
      "par_decay_slope": null
    },
    {
      "channel": "zone_permutation",
      "lambda": 1.0,
      "coupling_proxy": 0.5604,
      "par": 0.7595,
      "fpr": 0.0,
      "fnr": 0.2405,
      "par_ci_95": [
        0.6091,
        0.6956
      ],
      "par_zero": 0.6576,
      "par_zero_ci_95": [
        0.6151,
        0.7014
      ],
      "delta_proc": -0.0056,
      "delta_proc_ci_95": [
        -0.0167,
        0.0
      ],
      "par_decay_slope": -0.165
    },
    {
      "channel": "temporal_desync",
      "lambda": 0.0,
      "coupling_proxy": 1.0,
      "par": 0.9249,
      "fpr": 0.0089,
      "fnr": 0.0673,
      "par_ci_95": [
        0.9062,
        0.9287
      ],
      "par_zero": 0.9177,
      "par_zero_ci_95": [
        0.9062,
        0.9287
      ],
      "delta_proc": 0.0,
      "delta_proc_ci_95": [
        0.0,
        0.0
      ],
      "par_decay_slope": null
    },
    {
      "channel": "temporal_desync",
      "lambda": 0.25,
      "coupling_proxy": 1.0,
      "par": 0.9249,
      "fpr": 0.0089,
      "fnr": 0.0673,
      "par_ci_95": [
        0.9062,
        0.9287
      ],
      "par_zero": 0.9177,
      "par_zero_ci_95": [
        0.9062,
        0.9287
      ],
      "delta_proc": 0.0,
      "delta_proc_ci_95": [
        0.0,
        0.0
      ],
      "par_decay_slope": null
    },
    {
      "channel": "temporal_desync",
      "lambda": 0.5,
      "coupling_proxy": 0.9929,
      "par": 0.8831,
      "fpr": 0.0052,
      "fnr": 0.1128,
      "par_ci_95": [
        0.8579,
        0.8855
      ],
      "par_zero": 0.8718,
      "par_zero_ci_95": [
        0.8579,
        0.8855
      ],
      "delta_proc": 0.0,
      "delta_proc_ci_95": [
        0.0,
        0.0
      ],
      "par_decay_slope": null
    },
    {
      "channel": "temporal_desync",
      "lambda": 0.75,
      "coupling_proxy": 0.9907,
      "par": 0.8248,
      "fpr": 0.0056,
      "fnr": 0.1713,
      "par_ci_95": [
        0.7816,
        0.8135
      ],
      "par_zero": 0.7973,
      "par_zero_ci_95": [
        0.7816,
        0.8135
      ],
      "delta_proc": 0.0,
      "delta_proc_ci_95": [
        0.0,
        0.0
      ],
      "par_decay_slope": null
    },
    {
      "channel": "temporal_desync",
      "lambda": 1.0,
      "coupling_proxy": 0.9876,
      "par": 0.7684,
      "fpr": 0.006,
      "fnr": 0.228,
      "par_ci_95": [
        0.706,
        0.7441
      ],
      "par_zero": 0.7248,
      "par_zero_ci_95": [
        0.706,
        0.7441
      ],
      "delta_proc": 0.0,
      "delta_proc_ci_95": [
        0.0,
        0.0
      ],
      "par_decay_slope": -0.1652
    },
    {
      "channel": "noise_injection",
      "lambda": 0.0,
      "coupling_proxy": 1.0,
      "par": 0.9249,
      "fpr": 0.0089,
      "fnr": 0.0673,
      "par_ci_95": [
        0.9062,
        0.9287
      ],
      "par_zero": 0.9177,
      "par_zero_ci_95": [
        0.9062,
        0.9287
      ],
      "delta_proc": 0.0,
      "delta_proc_ci_95": [
        0.0,
        0.0
      ],
      "par_decay_slope": null
    },
    {
      "channel": "noise_injection",
      "lambda": 0.25,
      "coupling_proxy": 0.7908,
      "par": 0.7594,
      "fpr": 0.0159,
      "fnr": 0.2312,
      "par_ci_95": [
        0.7971,
        0.8469
      ],
      "par_zero": 0.8226,
      "par_zero_ci_95": [
        0.7971,
        0.8469
      ],
      "delta_proc": 0.0,
      "delta_proc_ci_95": [
        0.0,
        0.0
      ],
      "par_decay_slope": null
    },
    {
      "channel": "noise_injection",
      "lambda": 0.5,
      "coupling_proxy": 0.5862,
      "par": 0.6963,
      "fpr": 0.0228,
      "fnr": 0.2922,
      "par_ci_95": [
        0.7189,
        0.7732
      ],
      "par_zero": 0.7466,
      "par_zero_ci_95": [
        0.7189,
        0.7732
      ],
      "delta_proc": 0.0,
      "delta_proc_ci_95": [
        0.0,
        0.0
      ],
      "par_decay_slope": null
    },
    {
      "channel": "noise_injection",
      "lambda": 0.75,
      "coupling_proxy": 0.4461,
      "par": 0.6357,
      "fpr": 0.0399,
      "fnr": 0.347,
      "par_ci_95": [
        0.6454,
        0.7026
      ],
      "par_zero": 0.6742,
      "par_zero_ci_95": [
        0.6454,
        0.7026
      ],
      "delta_proc": 0.0,
      "delta_proc_ci_95": [
        0.0,
        0.0
      ],
      "par_decay_slope": null
    },
    {
      "channel": "noise_injection",
      "lambda": 1.0,
      "coupling_proxy": 0.3405,
      "par": 0.5893,
      "fpr": 0.0483,
      "fnr": 0.3925,
      "par_ci_95": [
        0.5892,
        0.6431
      ],
      "par_zero": 0.6164,
      "par_zero_ci_95": [
        0.5892,
        0.6431
      ],
      "delta_proc": 0.0,
      "delta_proc_ci_95": [
        0.0,
        0.0
      ],
      "par_decay_slope": -0.318
    }
  ],
  "run_count": 2700
}